src/__init__.py
src/cookie_validator.py
src/leetcode_notes_crawler.py
src/notifier.py
src/scheduler.py
utils/__init__.py
utils/api_detector.py
utils/debug_notes.py
utils/test_pagination.py
utils/verify_user.py
leetcode_obsidian_sync-1.1.0.dist-info/METADATA
leetcode_obsidian_sync-1.1.0.dist-info/WHEEL
leetcode_obsidian_sync-1.1.0.dist-info/entry_points.txt
leetcode_obsidian_sync-1.1.0.dist-info/top_level.txt
leetcode_obsidian_sync-1.1.0.dist-info/RECORD
