Metadata-Version: 2.4
Name: leetcode-obsidian-sync
Version: 1.1.0
Summary: 自动同步 LeetCode 笔记到 Obsidian/Markdown，支持增量更新、Cookie 自动检测和多种提醒方式
Author-email: Haoze Li <haoze.li@outlook.com>
Maintainer-email: Haoze Li <haoze.li@outlook.com>
License: MIT
Project-URL: Homepage, https://github.com/LiHaoze-Bob/LeetCodeUpdate
Project-URL: Repository, https://github.com/LiHaoze-Bob/LeetCodeUpdate
Project-URL: Bug Tracker, https://github.com/LiHaoze-Bob/LeetCodeUpdate/issues
Project-URL: Documentation, https://github.com/LiHaoze-Bob/LeetCodeUpdate#readme
Project-URL: Changelog, https://github.com/LiHaoze-Bob/LeetCodeUpdate/blob/main/docs/CHANGELOG.md
Keywords: leetcode,obsidian,sync,notes,markdown,crawler,automation,cookie-validator
Classifier: Development Status :: 4 - Beta
Classifier: Intended Audience :: Developers
Classifier: Intended Audience :: End Users/Desktop
Classifier: License :: OSI Approved :: MIT License
Classifier: Operating System :: OS Independent
Classifier: Programming Language :: Python :: 3
Classifier: Programming Language :: Python :: 3.8
Classifier: Programming Language :: Python :: 3.9
Classifier: Programming Language :: Python :: 3.10
Classifier: Programming Language :: Python :: 3.11
Classifier: Programming Language :: Python :: 3.12
Classifier: Topic :: Software Development :: Libraries :: Python Modules
Classifier: Topic :: Utilities
Requires-Python: >=3.8
Requires-Dist: requests>=2.31.0
Requires-Dist: python-dotenv>=1.0.0
Requires-Dist: schedule>=1.2.0
